{ "height":13,
 "layers":[
        {
         "data":[0, 0, 0, 0, 0, 0, 0, 18, 18, 18, 20, 18, 18, 22, 18, 18, 20, 18, 18, 18, 0, 0, 0, 0, 0, 0, 0, 0, 0, 0, 0, 0, 0, 0, 18, 51, 51, 51, 51, 51, 51, 51, 51, 51, 51, 51, 18, 0, 0, 0, 0, 0, 0, 0, 0, 0, 0, 0, 0, 0, 0, 18, 51, 51, 51, 51, 51, 51, 51, 51, 51, 51, 51, 18, 0, 0, 0, 0, 0, 0, 0, 0, 0, 0, 0, 0, 0, 0, 18, 51, 51, 51, 51, 51, 51, 51, 51, 51, 51, 51, 18, 0, 0, 0, 0, 0, 0, 0, 0, 0, 0, 0, 0, 0, 0, 18, 51, 51, 51, 51, 51, 51, 51, 51, 51, 51, 51, 18, 0, 0, 0, 0, 0, 0, 0, 0, 0, 0, 0, 0, 0, 0, 22, 51, 51, 51, 51, 51, 51, 51, 51, 51, 51, 51, 22, 0, 0, 0, 0, 0, 0, 0, 0, 0, 0, 0, 0, 0, 0, 22, 51, 51, 51, 51, 51, 51, 51, 51, 51, 51, 51, 22, 0, 0, 0, 0, 0, 0, 0, 0, 0, 0, 0, 0, 0, 0, 18, 51, 51, 51, 51, 51, 51, 51, 51, 51, 51, 51, 18, 0, 0, 0, 0, 0, 0, 0, 0, 0, 0, 0, 0, 0, 0, 18, 51, 51, 51, 51, 51, 51, 51, 51, 51, 51, 51, 18, 0, 0, 0, 0, 0, 0, 0, 0, 0, 0, 0, 0, 0, 0, 18, 51, 51, 51, 51, 51, 51, 51, 51, 51, 51, 51, 18, 0, 0, 0, 0, 0, 0, 0, 0, 0, 0, 0, 0, 0, 0, 18, 51, 51, 51, 51, 51, 51, 51, 51, 51, 51, 51, 18, 0, 0, 0, 0, 0, 0, 0, 0, 0, 0, 0, 0, 0, 0, 18, 51, 51, 51, 51, 51, 51, 51, 51, 51, 51, 51, 18, 0, 0, 0, 0, 0, 0, 0, 0, 0, 0, 0, 0, 0, 0, 18, 18, 18, 18, 18, 18, 22, 18, 18, 18, 18, 18, 18, 0, 0, 0, 0, 0, 0, 0],
         "height":13,
         "name":"TileLayer",
         "opacity":0.850000023841858,
         "type":"tilelayer",
         "visible":true,
         "width":27,
         "x":0,
         "y":0
        }],
 "nextobjectid":1,
 "orientation":"orthogonal",
 "renderorder":"right-down",
 "tiledversion":"1.0.3",
 "tileheight":32,
 "tilesets":[
        {
         "columns":16,
         "firstgid":1,
         "image":"tiles.png",
         "imageheight":512,
         "imagewidth":512,
         "margin":0,
         "name":"tiles",
         "spacing":0,
         "tilecount":256,
         "tileheight":32,
         "tilewidth":32
        }],
 "tilewidth":32,
 "type":"map",
 "version":1,
 "width":27
}